predicts/__init__.py
predicts/abstractest.py
predicts/prediction.py
predicts/utils.py
predicts-0.1.dist-info/METADATA
predicts-0.1.dist-info/WHEEL
predicts-0.1.dist-info/top_level.txt
predicts-0.1.dist-info/RECORD
