Metadata-Version: 2.1
Name: predicts
Version: 0.1
Summary: Predicting Titanic Survivor
Home-page: https://github.com/abbiyanaila/predicts
Author: Desi Ratna Ningsih
Author-email: abbiyanaila@gmail.com
License: MIT
Platform: UNKNOWN
